shared/__init__.py
shared/cli.py
shared/config.py
shared/error_helpers.py
shared/exceptions.py
shared/http_client.py
shared/json_helpers.py
shared/logging.py
shared/validation.py
zdatafetch/__init__.py
zdatafetch/activity.py
zdatafetch/auth.py
zdatafetch/cli.py
zdatafetch/config.py
zdatafetch/followers.py
zdatafetch/logging_config.py
zdatafetch/profile.py
zdatafetch/rideons.py
zdatafetch/ridersinworld.py
zdatafetch/worlds.py
zpdatafetch/__init__.py
zpdatafetch/async_zp.py
zpdatafetch/cli.py
zpdatafetch/config.py
zpdatafetch/logging_config.py
zpdatafetch/zp.py
zpdatafetch/zp_obj.py
zpdatafetch/zp_utils.py
zpdatafetch/zpcyclist.py
zpdatafetch/zpcyclistfetch.py
zpdatafetch/zpleague.py
zpdatafetch/zpleaguefetch.py
zpdatafetch/zpprime.py
zpdatafetch/zpprimesfetch.py
zpdatafetch/zpracefinish.py
zpdatafetch/zpracelog.py
zpdatafetch/zpraceresult.py
zpdatafetch/zpracesignup.py
zpdatafetch/zpracesprint.py
zpdatafetch/zpresultfetch.py
zpdatafetch/zpsignupfetch.py
zpdatafetch/zpsprintsfetch.py
zpdatafetch/zpteam.py
zpdatafetch/zpteamfetch.py
zpdatafetch-2.0.3.dist-info/licenses/LICENSE
zrdatafetch/__init__.py
zrdatafetch/async_zr.py
zrdatafetch/cli.py
zrdatafetch/config.py
zrdatafetch/logging_config.py
zrdatafetch/rate_limiter.py
zrdatafetch/zr.py
zrdatafetch/zr_utils.py
zrdatafetch/zrraceresult.py
zrdatafetch/zrresultfetch.py
zrdatafetch/zrrider.py
zrdatafetch/zrriderfetch.py
zrdatafetch/zrteamfetch.py
zrdatafetch/zrteamroster.py
zpdatafetch-2.0.3.dist-info/METADATA
zpdatafetch-2.0.3.dist-info/WHEEL
zpdatafetch-2.0.3.dist-info/entry_points.txt
zpdatafetch-2.0.3.dist-info/top_level.txt
zpdatafetch-2.0.3.dist-info/RECORD
