Metadata-Version: 2.4
Name: zpdatafetch
Version: 2.0.3
Summary: A package for fetching data from Zwiftpower and Zwiftracing.app
Author-email: Doug Morris <doug@mhost.com>
License-Expression: MIT
Project-URL: Homepage, https://github.com/puckdoug/zpdatafetch
Project-URL: Issues, https://github.com/puckdoug/zpdatafetch/issues
Project-URL: Repository, https://github.com/puckdoug/zpdatafetch
Keywords: cycling,data,racing,vELO,zwift,zwiftpower,zwiftracing
Requires-Python: >=3.10
License-File: LICENSE
Requires-Dist: anyio>=4.4.0
Requires-Dist: beautifulsoup4>=4.12.3
Requires-Dist: cryptography>=44.0.0
Requires-Dist: httpx>=0.28.0
Requires-Dist: keyring>=25.2.0
Requires-Dist: keyrings-alt
Requires-Dist: lxml>=5.4.0
Provides-Extra: async-full
Requires-Dist: trio>=0.26.0; extra == "async-full"
Provides-Extra: trio
Requires-Dist: trio>=0.26.0; extra == "trio"
Dynamic: license-file
